openrouter_client/__init__.py
openrouter_client/auth.py
openrouter_client/client.py
openrouter_client/exceptions.py
openrouter_client/http.py
openrouter_client/logging.py
openrouter_client/streaming.py
openrouter_client/tools.py
openrouter_client/types.py
openrouter_client/version.py
openrouter_client/endpoints/__init__.py
openrouter_client/endpoints/base.py
openrouter_client/endpoints/chat.py
openrouter_client/endpoints/completions.py
openrouter_client/endpoints/credits.py
openrouter_client/endpoints/generations.py
openrouter_client/endpoints/keys.py
openrouter_client/endpoints/models.py
openrouter_client/models/__init__.py
openrouter_client/models/attachment.py
openrouter_client/models/chat.py
openrouter_client/models/completions.py
openrouter_client/models/core.py
openrouter_client/models/credits.py
openrouter_client/models/generations.py
openrouter_client/models/llm.py
openrouter_client/models/models.py
openrouter_client/models/providers.py
openrouter_client_unofficial-0.0.4.dist-info/licenses/LICENSE
openrouter_client_unofficial-0.0.4.dist-info/METADATA
openrouter_client_unofficial-0.0.4.dist-info/WHEEL
openrouter_client_unofficial-0.0.4.dist-info/top_level.txt
openrouter_client_unofficial-0.0.4.dist-info/RECORD
