Metadata-Version: 2.4
Name: openrouter-client-unofficial
Version: 0.0.4
Summary: Unofficial Python client for the OpenRouter API, providing a comprehensive interface for interacting with large language models
Author-email: Ryan Taylor <ryan@beta-reduce.net>
License-Expression: Apache-2.0
Project-URL: Homepage, https://github.com/dingo-actual/openrouter-python-client
Project-URL: Documentation, https://github.com/dingo-actual/openrouter-python-client#readme
Project-URL: Repository, https://github.com/dingo-actual/openrouter-python-client
Project-URL: Issues, https://github.com/dingo-actual/openrouter-python-client/issues
Keywords: ai,api-client,openrouter,llm,large-language-models
Classifier: Development Status :: 3 - Alpha
Classifier: Programming Language :: Python :: 3
Classifier: Programming Language :: Python :: 3.9
Classifier: Programming Language :: Python :: 3.10
Classifier: Programming Language :: Python :: 3.11
Classifier: Programming Language :: Python :: 3.12
Classifier: Programming Language :: Python :: 3.13
Classifier: Operating System :: OS Independent
Classifier: Intended Audience :: Developers
Classifier: Topic :: Software Development :: Libraries :: Python Modules
Classifier: Topic :: Scientific/Engineering :: Artificial Intelligence
Requires-Python: >=3.9
License-File: LICENSE
Requires-Dist: pynacl>=1.0.0
Requires-Dist: pydantic>=2.0.0
Requires-Dist: smartsurge>=0.0.7
Requires-Dist: python-dateutil>=2.0.0
Provides-Extra: dev
Requires-Dist: packaging>=25.0.0; extra == "dev"
Requires-Dist: pytest>=8.3.5; extra == "dev"
Requires-Dist: pytest-asyncio>=0.21.0; extra == "dev"
Requires-Dist: pytest-cov>=6.0.0; extra == "dev"
Requires-Dist: black>=21.0.0; extra == "dev"
Requires-Dist: isort>=5.0.0; extra == "dev"
Requires-Dist: mypy>=1.0.0; extra == "dev"
Requires-Dist: flake8>=6.0.0; extra == "dev"
Provides-Extra: docs
Requires-Dist: mkdocs>=1.4.2; extra == "docs"
Requires-Dist: mkdocs-material>=9.0.0; extra == "docs"
Requires-Dist: mkdocstrings[python]>=0.20.0; extra == "docs"
Provides-Extra: phase
Requires-Dist: phase-cli>=1.15.0; extra == "phase"
Requires-Dist: wcwidth>=0.2.0; extra == "phase"
Dynamic: license-file
